bayesian_changepoint_detection/__init__.py
bayesian_changepoint_detection/bayesian_models.py
bayesian_changepoint_detection/cy_offline_changepoint_detection.py
bayesian_changepoint_detection/generate_data.py
bayesian_changepoint_detection/hazard_functions.py
bayesian_changepoint_detection/offline_likelihoods.py
bayesian_changepoint_detection/online_likelihoods.py
bayesian_changepoint_detection/priors.py
bayescd-0.4.dist-info/LICENSE
bayescd-0.4.dist-info/METADATA
bayescd-0.4.dist-info/WHEEL
bayescd-0.4.dist-info/top_level.txt
bayescd-0.4.dist-info/RECORD
